MANIFEST.in
README.md
setup.py
chandan/__init__.py
chandan/main.py
chandan.egg-info/PKG-INFO
chandan.egg-info/SOURCES.txt
chandan.egg-info/dependency_links.txt
chandan.egg-info/not-zip-safe
chandan.egg-info/top_level.txt