Metadata-Version: 1.0
Name: chandan
Version: 0.3
Summary: Chandan on the go
Home-page: https://github.com/csinva/chandan
Author: Chandan Singh
Author-email: csinva@yahoo.com
License: MIT
Platform: UNKNOWN
